ansible-playbook.yml
torrentdoer/__init__.py
torrentdoer/__main__.py
torrentdoer/constants.py
torrentdoer/create.py
torrentdoer/destroy.py
torrentdoer/droplet_helper.py
torrentdoer/entrypoint.py
torrentdoer/retrieve.py
torrentdoer/ssh.py
torrentdoer/sshconnect.py
torrentdoer-0.3.0.dist-info/entry_points.txt
torrentdoer-0.3.0.dist-info/WHEEL
torrentdoer-0.3.0.dist-info/METADATA
torrentdoer-0.3.0.dist-info/RECORD
