Metadata-Version: 2.1
Name: torrentdoer
Version: 0.3.0
Summary: Do your torrenting from DigitalOcean.
Home-page: https://github.com/tylergannon/torrentdoer
License: BSD-4-Clause
Author: Tyler Gannon
Author-email: tgannon@gmail.com
Requires-Python: >=3.9,<4.0
Classifier: License :: Other/Proprietary License
Classifier: Programming Language :: Python :: 3
Classifier: Programming Language :: Python :: 3.9
Requires-Dist: ansible (>=2.10.3,<3.0.0)
Requires-Dist: click (>=7.1.2,<8.0.0)
Requires-Dist: click-conf-file (>=0.1.2,<0.2.0)
Project-URL: Repository, https://github.com/tylergannon/torrentdoer
